cion/__init__.py
cion/converters.py
cion/exceptions.py
cion/options.py
cion/py.typed
cion/schema.py
cion/types.py
cion/validators.py
cion/ext/__init__.py
tests/__init__.py
tests/test_converters.py
tests/test_exceptions.py
tests/test_options.py
tests/test_schema.py
tests/test_types.py
tests/test_validators.py
cion-0.3.1.dist-info/LICENSE
cion-0.3.1.dist-info/METADATA
cion-0.3.1.dist-info/WHEEL
cion-0.3.1.dist-info/top_level.txt
cion-0.3.1.dist-info/RECORD
