Metadata-Version: 2.1
Name: cion
Version: 0.3.1
Summary: A data validation library
Home-page: https://github.com/meizuflux/cion
Author: meizuflux
License: MIT
Project-URL: Documentation, https://cionpy.readthedocs.io
Project-URL: Issue Tracker, https://github.com/meizuflux/cion/issues
Project-URL: Source Code, https://github.com/meizuflux/cion
Classifier: Intended Audience :: Developers
Classifier: Programming Language :: Python :: 3.10
Classifier: License :: OSI Approved :: MIT License
Classifier: Operating System :: OS Independent
Classifier: Typing :: Typed
Requires-Python: >=3.10
License-File: LICENSE
Provides-Extra: build
Requires-Dist: setuptools ; extra == 'build'
Requires-Dist: wheel ; extra == 'build'
Requires-Dist: build ; extra == 'build'
Requires-Dist: twine ; extra == 'build'
Provides-Extra: docs
Requires-Dist: sphinx ; extra == 'docs'
Requires-Dist: sphinx-copybutton ; extra == 'docs'
Provides-Extra: format
Requires-Dist: black ; extra == 'format'
Requires-Dist: isort ; extra == 'format'
Provides-Extra: lint
Requires-Dist: pyright ; extra == 'lint'
Provides-Extra: test
Requires-Dist: pytest ; extra == 'test'
Requires-Dist: coverage[toml] ; extra == 'test'
Requires-Dist: pytest-cov ; extra == 'test'
